pyleaves2/__init__.py
pyleaves2/leaves.py
pyleaves2/text_format.py
pyleaves2/utils.py
pyleaves2/PyroTools/__init__.py
pyleaves2/PyroTools/progress_message.py
PyLeaves2-1.0.2.dist-info/LICENSE
PyLeaves2-1.0.2.dist-info/METADATA
PyLeaves2-1.0.2.dist-info/WHEEL
PyLeaves2-1.0.2.dist-info/top_level.txt
PyLeaves2-1.0.2.dist-info/RECORD
