Metadata-Version: 2.1
Name: PyLeaves2
Version: 1.0.2
Summary: Python package for telegram bots and sub tool for pyrogram
Home-page: https://github.com/nafis01aa/PyLeaves2
Author: Nafis
License: GNU General Public License v3.0
Classifier: Programming Language :: Python :: 3
Classifier: License :: OSI Approved :: GNU Lesser General Public License v3 or later (LGPLv3+)
Classifier: Operating System :: OS Independent
Requires-Python: >=3.6
License-File: LICENSE
